better_timers/__init__.py
better_timers_gudninatan-0.0.3.dist-info/LICENSE
better_timers_gudninatan-0.0.3.dist-info/METADATA
better_timers_gudninatan-0.0.3.dist-info/WHEEL
better_timers_gudninatan-0.0.3.dist-info/top_level.txt
better_timers_gudninatan-0.0.3.dist-info/RECORD
