Metadata-Version: 2.1
Name: better-timers-gudninatan
Version: 0.0.3
Summary: Better timers for pygame
Home-page: https://github.com/GudniNatan/better_timers
Author: Guðni Natan Gunnarsson
Author-email: author@example.com
License: UNKNOWN
Platform: UNKNOWN
Classifier: Programming Language :: Python :: 3
Classifier: License :: OSI Approved :: MIT License
Classifier: Operating System :: OS Independent
Requires-Dist: pygame
